bq_validator/__init__.py
bq_validator/__main__.py
bq_validator/bigquery.py
bq_validator/cli.py
bq_validator/utils.py
bq_validator-0.9.1.dist-info/METADATA
bq_validator-0.9.1.dist-info/WHEEL
bq_validator-0.9.1.dist-info/entry_points.txt
bq_validator-0.9.1.dist-info/licenses/LICENSE
bq_validator-0.9.1.dist-info/RECORD
