Metadata-Version: 2.4
Name: bq-validator
Version: 0.9.1
Dynamic: Summary
Author: yu-iskw
License:                                  Apache License
License-File: LICENSE
Classifier: Development Status :: 4 - Beta
Classifier: Intended Audience :: Information Technology
Classifier: Intended Audience :: System Administrators
Classifier: License :: OSI Approved :: Apache Software License
Classifier: Operating System :: OS Independent
Classifier: Programming Language :: Python
Classifier: Programming Language :: Python :: 3
Classifier: Programming Language :: Python :: 3 :: Only
Classifier: Programming Language :: Python :: 3.10
Classifier: Programming Language :: Python :: 3.11
Classifier: Programming Language :: Python :: 3.12
Classifier: Programming Language :: Python :: 3.13
Classifier: Topic :: Software Development :: Libraries
Classifier: Topic :: Software Development :: Libraries :: Python Modules
Classifier: Typing :: Typed
Requires-Python: >=3.10
Requires-Dist: click-completion>=0.5.2
Requires-Dist: click<9.0.0,>=8.0.0
Requires-Dist: google-cloud-bigquery<4.0.0,>=1.25.0
Provides-Extra: dev
Requires-Dist: hatch>=0.23.1; extra == 'dev'
Requires-Dist: isort>=5.10.1; extra == 'dev'
Requires-Dist: mypy>=0.971; extra == 'dev'
Requires-Dist: pytest>=7.0.1; extra == 'dev'
Requires-Dist: ruff>=0.0.17; extra == 'dev'
